table_recognition_metric/__init__.py
table_recognition_metric/main.py
table_recognition_metric-0.0.4.dist-info/METADATA
table_recognition_metric-0.0.4.dist-info/WHEEL
table_recognition_metric-0.0.4.dist-info/entry_points.txt
table_recognition_metric-0.0.4.dist-info/top_level.txt
table_recognition_metric-0.0.4.dist-info/RECORD
