Metadata-Version: 2.1
Name: table-recognition-metric
Version: 0.0.4
Summary: Tool of computing the TEDS of table recognition
Home-page: https://github.com/SWHL/TableRecognitionMetric
Author: SWHL
Author-email: liekkaskono@163.com
License: Apache-2.0
Keywords: ocr, table-recognition
Platform: Any
Classifier: Programming Language :: Python :: 3.6
Classifier: Programming Language :: Python :: 3.7
Classifier: Programming Language :: Python :: 3.8
Classifier: Programming Language :: Python :: 3.9
Classifier: Programming Language :: Python :: 3.10
Classifier: Programming Language :: Python :: 3.11
Requires-Python: >=3.6,<3.12
Requires-Dist: apted >=1.0.3
Requires-Dist: lxml >=4.9.3
Requires-Dist: levenshtein
